{"v":4,"entries":{"components-atoms-accordion--docs":{"id":"components-atoms-accordion--docs","title":"Components/Atoms/Accordion","name":"Docs","importPath":"./src/stories/atoms/Accordion.stories.tsx","type":"docs","storiesImports":[],"standalone":false},"components-atoms-accordion--accordion":{"id":"components-atoms-accordion--accordion","title":"Components/Atoms/Accordion","name":"Accordion","importPath":"./src/stories/atoms/Accordion.stories.tsx","type":"story"},"components-atoms-badge--docs":{"id":"components-atoms-badge--docs","title":"Components/Atoms/Badge","name":"Docs","importPath":"./src/stories/atoms/Badge.stories.tsx","type":"docs","storiesImports":[],"standalone":false},"components-atoms-badge--badge":{"id":"components-atoms-badge--badge","title":"Components/Atoms/Badge","name":"Badge","importPath":"./src/stories/atoms/Badge.stories.tsx","type":"story"},"components-atoms-buttons--docs":{"id":"components-atoms-buttons--docs","title":"Components/Atoms/Buttons","name":"Docs","importPath":"./src/stories/atoms/Button.stories.tsx","type":"docs","storiesImports":[],"standalone":false},"components-atoms-buttons--buttons":{"id":"components-atoms-buttons--buttons","title":"Components/Atoms/Buttons","name":"Buttons","importPath":"./src/stories/atoms/Button.stories.tsx","type":"story"},"components-atoms-cards--docs":{"id":"components-atoms-cards--docs","title":"Components/Atoms/Cards","name":"Docs","importPath":"./src/stories/atoms/Card.stories.tsx","type":"docs","storiesImports":[],"standalone":false},"components-atoms-cards--cards":{"id":"components-atoms-cards--cards","title":"Components/Atoms/Cards","name":"Cards","importPath":"./src/stories/atoms/Card.stories.tsx","type":"story"},"components-atoms-checkbox--docs":{"id":"components-atoms-checkbox--docs","title":"Components/Atoms/Checkbox","name":"Docs","importPath":"./src/stories/atoms/Checkbox.stories.tsx","type":"docs","storiesImports":[],"standalone":false},"components-atoms-checkbox--checkbox":{"id":"components-atoms-checkbox--checkbox","title":"Components/Atoms/Checkbox","name":"Checkbox","importPath":"./src/stories/atoms/Checkbox.stories.tsx","type":"story"},"components-atoms-heading--docs":{"id":"components-atoms-heading--docs","title":"Components/Atoms/Heading","name":"Docs","importPath":"./src/stories/atoms/Heading.stories.tsx","type":"docs","storiesImports":[],"standalone":false},"components-atoms-heading--heading":{"id":"components-atoms-heading--heading","title":"Components/Atoms/Heading","name":"Heading","importPath":"./src/stories/atoms/Heading.stories.tsx","type":"story"},"components-atoms-input--docs":{"id":"components-atoms-input--docs","title":"Components/Atoms/Input","name":"Docs","importPath":"./src/stories/atoms/Input.stories.tsx","type":"docs","storiesImports":[],"standalone":false},"components-atoms-input--input":{"id":"components-atoms-input--input","title":"Components/Atoms/Input","name":"Input","importPath":"./src/stories/atoms/Input.stories.tsx","type":"story"},"components-atoms-list--docs":{"id":"components-atoms-list--docs","title":"Components/Atoms/List","name":"Docs","importPath":"./src/stories/atoms/List.stories.tsx","type":"docs","storiesImports":[],"standalone":false},"components-atoms-list--list":{"id":"components-atoms-list--list","title":"Components/Atoms/List","name":"List","importPath":"./src/stories/atoms/List.stories.tsx","type":"story"},"components-atoms-menu--docs":{"id":"components-atoms-menu--docs","title":"Components/Atoms/Menu","name":"Docs","importPath":"./src/stories/atoms/Menu.stories.tsx","type":"docs","storiesImports":[],"standalone":false},"components-atoms-menu--menu":{"id":"components-atoms-menu--menu","title":"Components/Atoms/Menu","name":"Menu","importPath":"./src/stories/atoms/Menu.stories.tsx","type":"story"},"components-atoms-radio--docs":{"id":"components-atoms-radio--docs","title":"Components/Atoms/Radio","name":"Docs","importPath":"./src/stories/atoms/Radio.stories.tsx","type":"docs","storiesImports":[],"standalone":false},"components-atoms-radio--radio":{"id":"components-atoms-radio--radio","title":"Components/Atoms/Radio","name":"Radio","importPath":"./src/stories/atoms/Radio.stories.tsx","type":"story"},"components-atoms-select--docs":{"id":"components-atoms-select--docs","title":"Components/Atoms/Select","name":"Docs","importPath":"./src/stories/atoms/Select.stories.tsx","type":"docs","storiesImports":[],"standalone":false},"components-atoms-select--select":{"id":"components-atoms-select--select","title":"Components/Atoms/Select","name":"Select","importPath":"./src/stories/atoms/Select.stories.tsx","type":"story"},"components-atoms-slider--docs":{"id":"components-atoms-slider--docs","title":"Components/Atoms/Slider","name":"Docs","importPath":"./src/stories/atoms/Slider.stories.tsx","type":"docs","storiesImports":[],"standalone":false},"components-atoms-slider--slider":{"id":"components-atoms-slider--slider","title":"Components/Atoms/Slider","name":"Slider","importPath":"./src/stories/atoms/Slider.stories.tsx","type":"story"},"components-atoms-spinner--docs":{"id":"components-atoms-spinner--docs","title":"Components/Atoms/Spinner","name":"Docs","importPath":"./src/stories/atoms/Spinner.stories.tsx","type":"docs","storiesImports":[],"standalone":false},"components-atoms-spinner--spinner":{"id":"components-atoms-spinner--spinner","title":"Components/Atoms/Spinner","name":"Spinner","importPath":"./src/stories/atoms/Spinner.stories.tsx","type":"story"},"components-atoms-switch--docs":{"id":"components-atoms-switch--docs","title":"Components/Atoms/Switch","name":"Docs","importPath":"./src/stories/atoms/Switch.stories.tsx","type":"docs","storiesImports":[],"standalone":false},"components-atoms-switch--switch":{"id":"components-atoms-switch--switch","title":"Components/Atoms/Switch","name":"Switch","importPath":"./src/stories/atoms/Switch.stories.tsx","type":"story"},"components-atoms-tabs--docs":{"id":"components-atoms-tabs--docs","title":"Components/Atoms/Tabs","name":"Docs","importPath":"./src/stories/atoms/Tabs.stories.tsx","type":"docs","storiesImports":[],"standalone":false},"components-atoms-tabs--tabs":{"id":"components-atoms-tabs--tabs","title":"Components/Atoms/Tabs","name":"Tabs","importPath":"./src/stories/atoms/Tabs.stories.tsx","type":"story"},"components-atoms-tags--docs":{"id":"components-atoms-tags--docs","title":"Components/Atoms/Tags","name":"Docs","importPath":"./src/stories/atoms/Tag.stories.tsx","type":"docs","storiesImports":[],"standalone":false},"components-atoms-tags--tags":{"id":"components-atoms-tags--tags","title":"Components/Atoms/Tags","name":"Tags","importPath":"./src/stories/atoms/Tag.stories.tsx","type":"story"},"components-atoms-text--docs":{"id":"components-atoms-text--docs","title":"Components/Atoms/Text","name":"Docs","importPath":"./src/stories/atoms/Text.stories.tsx","type":"docs","storiesImports":[],"standalone":false},"components-atoms-text--text":{"id":"components-atoms-text--text","title":"Components/Atoms/Text","name":"Text","importPath":"./src/stories/atoms/Text.stories.tsx","type":"story"},"components-atoms-textarea--docs":{"id":"components-atoms-textarea--docs","title":"Components/Atoms/Textarea","name":"Docs","importPath":"./src/stories/atoms/Textarea.stories.tsx","type":"docs","storiesImports":[],"standalone":false},"components-atoms-textarea--textarea":{"id":"components-atoms-textarea--textarea","title":"Components/Atoms/Textarea","name":"Textarea","importPath":"./src/stories/atoms/Textarea.stories.tsx","type":"story"},"components-atoms-toast--docs":{"id":"components-atoms-toast--docs","title":"Components/Atoms/Toast","name":"Docs","importPath":"./src/stories/atoms/Toast.stories.tsx","type":"docs","storiesImports":[],"standalone":false},"components-atoms-toast--toast":{"id":"components-atoms-toast--toast","title":"Components/Atoms/Toast","name":"Toast","importPath":"./src/stories/atoms/Toast.stories.tsx","type":"story"},"components-atoms-tooltip--docs":{"id":"components-atoms-tooltip--docs","title":"Components/Atoms/Tooltip","name":"Docs","importPath":"./src/stories/atoms/Tooltip.stories.tsx","type":"docs","storiesImports":[],"standalone":false},"components-atoms-tooltip--tooltip":{"id":"components-atoms-tooltip--tooltip","title":"Components/Atoms/Tooltip","name":"Tooltip","importPath":"./src/stories/atoms/Tooltip.stories.tsx","type":"story"},"components-atoms-icons--docs":{"id":"components-atoms-icons--docs","title":"Components/Atoms/Icons","name":"Docs","importPath":"./src/stories/icons/Icons.stories.tsx","type":"docs","storiesImports":[],"standalone":false},"components-atoms-icons--icons":{"id":"components-atoms-icons--icons","title":"Components/Atoms/Icons","name":"Icons","importPath":"./src/stories/icons/Icons.stories.tsx","type":"story"},"raid-guild-design-system--docs":{"id":"raid-guild-design-system--docs","title":"Raid Guild Design System","name":"Docs","importPath":"./src/stories/index.stories.tsx","type":"docs","storiesImports":[],"standalone":false},"raid-guild-design-system--index":{"id":"raid-guild-design-system--index","title":"Raid Guild Design System","name":"Index","importPath":"./src/stories/index.stories.tsx","type":"story"},"system-colors--docs":{"id":"system-colors--docs","title":"System/Colors","name":"Docs","importPath":"./src/stories/misc/colors.stories.tsx","type":"docs","storiesImports":[],"standalone":false},"system-colors--colors":{"id":"system-colors--colors","title":"System/Colors","name":"Colors","importPath":"./src/stories/misc/colors.stories.tsx","type":"story"},"system-spacing--docs":{"id":"system-spacing--docs","title":"System/Spacing","name":"Docs","importPath":"./src/stories/misc/spacing.stories.tsx","type":"docs","storiesImports":[],"standalone":false},"system-spacing--spacing":{"id":"system-spacing--spacing","title":"System/Spacing","name":"Spacing","importPath":"./src/stories/misc/spacing.stories.tsx","type":"story"},"components-molecules-alert-dialog--docs":{"id":"components-molecules-alert-dialog--docs","title":"Components/Molecules/Alert Dialog","name":"Docs","importPath":"./src/stories/molecules/AlertDialog.stories.tsx","type":"docs","storiesImports":[],"standalone":false},"components-molecules-alert-dialog--alert-dialog":{"id":"components-molecules-alert-dialog--alert-dialog","title":"Components/Molecules/Alert Dialog","name":"Alert Dialog","importPath":"./src/stories/molecules/AlertDialog.stories.tsx","type":"story"},"components-molecules-builtbyraidguild--docs":{"id":"components-molecules-builtbyraidguild--docs","title":"Components/Molecules/BuiltByRaidGuild","name":"Docs","importPath":"./src/stories/molecules/BuiltByRaidGuild.stories.tsx","type":"docs","storiesImports":[],"standalone":false},"components-molecules-builtbyraidguild--built-by-raid-guild":{"id":"components-molecules-builtbyraidguild--built-by-raid-guild","title":"Components/Molecules/BuiltByRaidGuild","name":"BuiltByRaidGuild","importPath":"./src/stories/molecules/BuiltByRaidGuild.stories.tsx","type":"story"},"components-molecules-buttongroup--docs":{"id":"components-molecules-buttongroup--docs","title":"Components/Molecules/ButtonGroup","name":"Docs","importPath":"./src/stories/molecules/ButtonGroup.stories.tsx","type":"docs","storiesImports":[],"standalone":false},"components-molecules-buttongroup--attached":{"id":"components-molecules-buttongroup--attached","title":"Components/Molecules/ButtonGroup","name":"Attached","importPath":"./src/stories/molecules/ButtonGroup.stories.tsx","type":"story"},"components-molecules-buttongroup--spaced":{"id":"components-molecules-buttongroup--spaced","title":"Components/Molecules/ButtonGroup","name":"Spaced","importPath":"./src/stories/molecules/ButtonGroup.stories.tsx","type":"story"},"components-molecules-modal--docs":{"id":"components-molecules-modal--docs","title":"Components/Molecules/Modal","name":"Docs","importPath":"./src/stories/molecules/Modal.stories.tsx","type":"docs","storiesImports":[],"standalone":false},"components-molecules-modal--modal":{"id":"components-molecules-modal--modal","title":"Components/Molecules/Modal","name":"Modal","importPath":"./src/stories/molecules/Modal.stories.tsx","type":"story"},"components-molecules-rolebadges--docs":{"id":"components-molecules-rolebadges--docs","title":"Components/Molecules/RoleBadges","name":"Docs","importPath":"./src/stories/molecules/RoleBadge.stories.tsx","type":"docs","storiesImports":[],"standalone":false},"components-molecules-rolebadges--role-badges":{"id":"components-molecules-rolebadges--role-badges","title":"Components/Molecules/RoleBadges","name":"Role Badges","importPath":"./src/stories/molecules/RoleBadge.stories.tsx","type":"story"}}}
